{
  "id": "michael_burry",
  "name": "迈克尔·伯里",
  "name_en": "Michael Burry",
  "era": "2000-至今",
  "background": "Scion Capital创始人，《大空头》原型。以在2008年金融危机前做空CDO闻名。专注于深度价值投资，寻找被市场忽视的标的。",
  "core_principles": [
    "深度价值",
    "反向投资",
    "基本面分析",
    "长期持有",
    "独立思考"
  ],
  "methodology": "深入研究公司基本面，寻找市场定价错误的标的。偏好简单、可理解、有现金流的业务。不介意逆势而行。愿意等待数年直到价值实现。极度重视风险控制。",
  "applicable_conditions": [
    "被市场冷落的价值股",
    "深度价值股",
    "危机中受压但基本面健康的标的",
    "分拆业务",
    "资产管理行业机会"
  ],
  "limitations": [
    "需要极强耐心",
    "逆向思维容易过早",
    "流动性风险",
    "不擅长成长股",
    "心理压力大"
  ],
  "quotes": [
    "市场总是过度反应，这就是机会所在。",
    "最大的风险是你不知道自己在做什么。",
    "我从不随大流。",
    "投资需要勇气，尤其是与共识相反时。",
    "成功的投资是找到正确的不对称。"
  ]
}